autotunenet/__init__.py
autotunenet/bayesian_optimizer.py
autotunenet/metrics.py
autotunenet/optimizer.py
autotunenet/optimizer_test.py
autotunenet/parameters.py
autotunenet/adapters/__init__.py
autotunenet/adapters/pytorch/__init__.py
autotunenet/adapters/pytorch/adapter.py
autotunenet/adapters/pytorch/hooks.py
autotunenet/adapters/pytorch/utils.py
autotunenet/config/__init__.py
autotunenet/config/loader.py
autotunenet/config/schema.py
autotunenet/exceptions/__init__.py
autotunenet/exceptions/exception.py
autotunenet/logging/__init__.py
autotunenet/logging/error_handler.py
autotunenet/logging/global_exception.py
autotunenet/logging/logger.py
autotunenet/logging/tracker.py
autotunenet/safeguards/__init__.py
autotunenet/safeguards/rollback.py
autotunenet/safeguards/stability.py
autotunenet/sandbox/__init__.py
autotunenet/sandbox/sandbox_test.py
autotunenet-1.0.1.dist-info/METADATA
autotunenet-1.0.1.dist-info/WHEEL
autotunenet-1.0.1.dist-info/top_level.txt
autotunenet-1.0.1.dist-info/RECORD
