Metadata-Version: 2.4
Name: autotunenet
Version: 1.0.1
Summary: Generic Bayesian self-optimizing hyperparameter tuning engine
Author-email: Mitish Raina <mitishraina.dev@gmail.com>
License: MIT
Project-URL: Homepage, https://github.com/mitishraina/AutoTuneNet
Project-URL: Repository, https://github.com/mitishraina/AutoTuneNet
Project-URL: Issues, https://github.com/mitishraina/AutoTuneNet/issues
Requires-Python: >=3.10
Requires-Dist: optuna
Requires-Dist: torch
Requires-Dist: torchvision
Requires-Dist: pyyaml
Provides-Extra: dev
Requires-Dist: pytest; extra == "dev"
Requires-Dist: black; extra == "dev"
Requires-Dist: ruff; extra == "dev"
